{"results": {"A": {"status": 200, "frames": [{"schema": {"refId": "A", "meta": {"type": "timeseries-multi", "typeVersion": [0, 1], "custom": {"resultType": "matrix"}, "executedQueryString": "Expr: count(time() - wireguard_latest_handshake_seconds{interface=\"wg0\", instance=\"10.1.0.1:9586\"} < 170)\nStep: 15s"}, "fields": [{"name": "Time", "type": "time", "typeInfo": {"frame": "time.Time"}, "config": {"interval": 15000}}, {"name": "Value", "type": "number", "typeInfo": {"frame": "float64"}, "labels": {}, "config": {"displayNameFromDS": "Server 1"}}]}, "data": {"values": [[1698658905000, 1698658920000, 1698658935000, 1698658950000, 1698658965000], [300, 300, 300, 300, 300]]}}]}, "B": {"status": 200, "frames": [{"schema": {"refId": "B", "meta": {"type": "timeseries-multi", "typeVersion": [0, 1], "custom": {"resultType": "matrix"}, "executedQueryString": "Expr: count(time() - wireguard_latest_handshake_seconds{interface=\"wg0\", instance=\"10.2.0.1:9586\"} < 170)\nStep: 15s"}, "fields": [{"name": "Time", "type": "time", "typeInfo": {"frame": "time.Time"}, "config": {"interval": 15000}}, {"name": "Value", "type": "number", "typeInfo": {"frame": "float64"}, "labels": {}, "config": {"displayNameFromDS": "Server 2"}}]}, "data": {"values": [[1698659010000, 1698659025000, 1698659040000, 1698659055000, 1698659070000, 1698659085000, 1698659100000, 1698659115000, 1698659130000, 1698659145000, 1698659160000, 1698659175000, 1698659190000, 1698659205000, 1698659220000, 1698659235000, 1698659250000, 1698659265000, 1698659280000, 1698659295000, 1698659310000, 1698659325000, 1698659340000, 1698659355000, 1698659370000, 1698659385000, 1698659400000, 1698659415000, 1698659430000, 1698659445000, 1698659460000, 1698659475000, 1698659490000, 1698659505000], [145, 145, 145, 222, 300, 300, 300, 300, 300, 300, 300, 300, 300, 300, 300, 300, 300, 300, 300, 300, 300, 300, 300, 300, 300, 300, 300, 300, 300, 300, 300, 300, 300, 300]]}}]}}}